[{"web_address": "https://www.otpbank.ro/hu/valutarfolyam", "currency": "EUR", "purchase_price": "1.158", "sale_price": "1.173"}, {"web_address": "https://www.otpbank.ro/hu/valutarfolyam", "currency": "USD", "purchase_price": "1.279", "sale_price": "1.283"}, {"web_address": "https://www.otpbank.ro/hu/valutarfolyam", "currency": "RON", "purchase_price": "5.428", "sale_price": "5.672"}, {"web_address": "http://www.lillapanzio.ro/valutavalto", "currency": "EUR", "purchase_price": "1.153", "sale_price": "1.158"}, {"web_address": "http://www.lillapanzio.ro/valutavalto", "currency": "USD", "purchase_price": "1.277", "sale_price": "1.277"}, {"web_address": "http://www.lillapanzio.ro/valutavalto", "currency": "RON", "purchase_price": "5.480", "sale_price": "5.520"}, {"web_address": "https://www.curs-valutar-bnr.ro/curs-valutar-banci/unicredit-tiriac-bank", "currency": "EUR", "purchase_price": "1.157", "sale_price": "1.175"}, {"web_address": "https://www.curs-valutar-bnr.ro/curs-valutar-banci/unicredit-tiriac-bank", "currency": "USD", "purchase_price": "1.283", "sale_price": "1.285"}, {"web_address": "https://www.curs-valutar-bnr.ro/curs-valutar-banci/unicredit-tiriac-bank", "currency": "RON", "purchase_price": "5.430", "sale_price": "5.680"}]